ncbi/__init__.py
ncbi/datasets/__init__.py
ncbi/datasets/openapi/__init__.py
ncbi/datasets/openapi/api_client.py
ncbi/datasets/openapi/api_response.py
ncbi/datasets/openapi/configuration.py
ncbi/datasets/openapi/exceptions.py
ncbi/datasets/openapi/py.typed
ncbi/datasets/openapi/rest.py
ncbi/datasets/openapi/api/__init__.py
ncbi/datasets/openapi/api/bio_sample_api.py
ncbi/datasets/openapi/api/gene_api.py
ncbi/datasets/openapi/api/genome_api.py
ncbi/datasets/openapi/api/organelle_api.py
ncbi/datasets/openapi/api/prokaryote_api.py
ncbi/datasets/openapi/api/taxonomy_api.py
ncbi/datasets/openapi/api/version_api.py
ncbi/datasets/openapi/api/virus_api.py
ncbi/datasets/openapi/models/__init__.py
ncbi/datasets/openapi/models/ncbigsupgcolv2_assembly_accessions_reply.py
ncbi/datasets/openapi/models/ncbigsupgcolv2_assembly_check_m_histogram_request.py
ncbi/datasets/openapi/models/ncbigsupgcolv2_assembly_data_report_draft_request.py
ncbi/datasets/openapi/models/ncbigsupgcolv2_assembly_data_reports_request.py
ncbi/datasets/openapi/models/ncbigsupgcolv2_chromosome_location.py
ncbi/datasets/openapi/models/ncbigsupgcolv2_chromosome_type.py
ncbi/datasets/openapi/models/ncbigsupgcolv2_sequence_accession_request.py
ncbi/datasets/openapi/models/ncbiprotddv2_chain_footprint.py
ncbi/datasets/openapi/models/ncbiprotddv2_query_structure_definition.py
ncbi/datasets/openapi/models/ncbiprotddv2_redundancy_level.py
ncbi/datasets/openapi/models/ncbiprotddv2_sdid_request.py
ncbi/datasets/openapi/models/ncbiprotddv2_similar_structure_report.py
ncbi/datasets/openapi/models/ncbiprotddv2_similar_structure_report_page.py
ncbi/datasets/openapi/models/ncbiprotddv2_similar_structure_request.py
ncbi/datasets/openapi/models/ncbiprotddv2_sort_by_id.py
ncbi/datasets/openapi/models/ncbiprotddv2_structure_data_report.py
ncbi/datasets/openapi/models/ncbiprotddv2_structure_data_report_biounit_chain.py
ncbi/datasets/openapi/models/ncbiprotddv2_structure_data_report_experiment.py
ncbi_datasets_pyclient-18.15.0.dist-info/licenses/LICENSE
ncbi_datasets_pyclient-18.15.0.dist-info/METADATA
ncbi_datasets_pyclient-18.15.0.dist-info/WHEEL
ncbi_datasets_pyclient-18.15.0.dist-info/top_level.txt
ncbi_datasets_pyclient-18.15.0.dist-info/RECORD
