Metadata-Version: 2.4
Name: ncbi-datasets-pyclient
Version: 18.15.0
Summary: NCBI Datasets API
Home-page: 
Author: NCBI
Author-email: NCBI <help@ncbi.nlm.nih.gov>
Project-URL: Repository, https://github.com/misialq/ncbi-datasets-pyclient
Keywords: OpenAPI,OpenAPI-Generator,NCBI Datasets API
Requires-Python: >=3.9
License-File: LICENSE
Requires-Dist: urllib3<3.0.0,>=2.1.0
Requires-Dist: python-dateutil>=2.8.2
Requires-Dist: pydantic>=2
Requires-Dist: typing-extensions>=4.7.1
Dynamic: author
Dynamic: license-file
